{"dependencies":[{"name":"/Users/macuser/Documents/projects/input/package.json","includedInParent":true,"mtime":1530687434000},{"name":"./script/*.js","loc":{"line":1,"column":7}},{"name":"./style/main.sass","loc":{"line":2,"column":7}}],"generated":{"js":"'use strict';\n\nrequire('./script/*.js');\n\nrequire('./style/main.sass');","map":{"mappings":[{"generated":{"line":3,"column":0},"source":"app.js","original":{"line":1,"column":0}},{"generated":{"line":5,"column":0},"source":"app.js","original":{"line":2,"column":0}}],"sources":{"app.js":"import './script/*.js'\nimport './style/main.sass'\n"},"lineCount":null}},"hash":"cceb310d15b2a135b88548bad07b3348","cacheData":{"env":{}}}